ovobdkit/__init__.py
ovobdkit/run_try.py
ovobdkit/ovodevkit/__init__.py
ovobdkit/ovodevkit/base_task.py
ovobdkit/ovodevkit/hive2hive.py
ovobdkit/ovodevkit/mysql2hive.py
ovobdkit/ovodevkit/pgsql2hive.py
ovobdkit/ovodevkit/typing.py
ovobdkit/ovodevkit/utils.py
ovobdkit/ovotestkit/__init__.py
ovobdkit/ovotestkit/func.py
ovobdkit/ovotestkit/source.py
ovobdkit/ovotestkit/unit.py
ovotestkit/__init__.py
ovotestkit/func.py
ovotestkit/unit.py
ovotestkit-1.0.0.dev0.dist-info/METADATA
ovotestkit-1.0.0.dev0.dist-info/WHEEL
ovotestkit-1.0.0.dev0.dist-info/top_level.txt
ovotestkit-1.0.0.dev0.dist-info/RECORD
