Metadata-Version: 2.1
Name: ovotestkit
Version: 1.0.0.dev0
Summary: Testing Kit for OVO Big Data
Home-page: https://github.com/pypa/sampleproject
Author: OVO BD Enginners, Zaky Rahim
Author-email: bd-engineers@ovo.id, zaky.rahim@ovo.id
License: UNKNOWN
Platform: UNKNOWN
Classifier: Programming Language :: Python :: 3
Classifier: License :: OSI Approved :: MIT License
Classifier: Operating System :: OS Independent
Requires-Python: >=3.6
Requires-Dist: psycopg2-binary
Requires-Dist: pandas
Requires-Dist: pyspark
Requires-Dist: bash
Requires-Dist: sqlalchemy
